randmac/__init__.py
randmac/__main__.py
randmac/__version__.py
randmac/helpers.py
randmac/randmac.py
randmac-0.1.dist-info/LICENSE
randmac-0.1.dist-info/METADATA
randmac-0.1.dist-info/WHEEL
randmac-0.1.dist-info/entry_points.txt
randmac-0.1.dist-info/top_level.txt
randmac-0.1.dist-info/RECORD
