Metadata-Version: 2.1
Name: randmac
Version: 0.1
Summary: a random 12-digit mac address generator
Home-page: https://github.com/joshschmelzle/randmac
Author: Josh Schmelzle
Author-email: josh@joshschmelzle.com
License: MIT
Keywords: randmac,random mac,random mac address
Platform: UNKNOWN
Classifier: Natural Language :: English
Classifier: Development Status :: 3 - Alpha
Classifier: Programming Language :: Python :: 3.2
Classifier: Intended Audience :: Developers
Classifier: Intended Audience :: System Administrators
Classifier: Topic :: Utilities
Requires-Python: >3.2,
